co2_potential/__init__.py
co2_potential/benchmark.py
co2_potential/libCO2CO2.so
co2_potential/wrapper.py
co2_potential-0.4.3.dist-info/licenses/LICENSE
co2_potential-0.4.3.dist-info/METADATA
co2_potential-0.4.3.dist-info/WHEEL
co2_potential-0.4.3.dist-info/entry_points.txt
co2_potential-0.4.3.dist-info/top_level.txt
co2_potential-0.4.3.dist-info/RECORD
