Metadata-Version: 2.4
Name: co2_potential
Version: 0.4.3
Summary: A Python package interfacing with the CO2CO2 shared library.
Author: Olaseni Sode
Author-email: osode@calstatela.edu
License: MIT
Classifier: Programming Language :: Python :: 3
Classifier: Programming Language :: C++
Classifier: Operating System :: MacOS :: MacOS X
Classifier: Operating System :: POSIX :: Linux
Requires-Python: >=3.6
License-File: LICENSE
Dynamic: author
Dynamic: author-email
Dynamic: classifier
Dynamic: description
Dynamic: description-content-type
Dynamic: license
Dynamic: license-file
Dynamic: requires-python
Dynamic: summary
